odoo/addons/l10n_jp_summary_invoice_carryover/README.rst
odoo/addons/l10n_jp_summary_invoice_carryover/__init__.py
odoo/addons/l10n_jp_summary_invoice_carryover/__manifest__.py
odoo/addons/l10n_jp_summary_invoice_carryover/i18n/ja.po
odoo/addons/l10n_jp_summary_invoice_carryover/i18n/l10n_jp_summary_invoice_carryover.pot
odoo/addons/l10n_jp_summary_invoice_carryover/models/__init__.py
odoo/addons/l10n_jp_summary_invoice_carryover/models/account_billing.py
odoo/addons/l10n_jp_summary_invoice_carryover/models/res_company.py
odoo/addons/l10n_jp_summary_invoice_carryover/models/res_config_settings.py
odoo/addons/l10n_jp_summary_invoice_carryover/models/res_partner.py
odoo/addons/l10n_jp_summary_invoice_carryover/readme/CONFIGURE.md
odoo/addons/l10n_jp_summary_invoice_carryover/readme/CONTRIBUTORS.md
odoo/addons/l10n_jp_summary_invoice_carryover/readme/DESCRIPTION.md
odoo/addons/l10n_jp_summary_invoice_carryover/readme/USAGE.md
odoo/addons/l10n_jp_summary_invoice_carryover/reports/report_summary_invoice_templates.xml
odoo/addons/l10n_jp_summary_invoice_carryover/static/description/icon.png
odoo/addons/l10n_jp_summary_invoice_carryover/static/description/index.html
odoo/addons/l10n_jp_summary_invoice_carryover/tests/__init__.py
odoo/addons/l10n_jp_summary_invoice_carryover/tests/test_l10n_jp_summary_invoice_carryover.py
odoo/addons/l10n_jp_summary_invoice_carryover/views/account_billing_views.xml
odoo/addons/l10n_jp_summary_invoice_carryover/views/res_config_settings_views.xml
odoo/addons/l10n_jp_summary_invoice_carryover/views/res_partner_views.xml
odoo_addon_l10n_jp_summary_invoice_carryover-18.0.1.0.0.2.dist-info/METADATA
odoo_addon_l10n_jp_summary_invoice_carryover-18.0.1.0.0.2.dist-info/WHEEL
odoo_addon_l10n_jp_summary_invoice_carryover-18.0.1.0.0.2.dist-info/top_level.txt
odoo_addon_l10n_jp_summary_invoice_carryover-18.0.1.0.0.2.dist-info/RECORD
