Metadata-Version: 2.1
Name: odoo-addon-l10n_jp_summary_invoice_carryover
Version: 18.0.1.0.0.2
Requires-Python: >=3.10
Requires-Dist: odoo-addon-l10n_jp_summary_invoice==18.0.*
Requires-Dist: odoo==18.0.*
Summary: Add carryover amount tracking to summary invoices
Home-page: https://github.com/OCA/l10n-japan
License: AGPL-3
Author: Quartile, Odoo Community Association (OCA)
Author-email: support@odoo-community.org
Classifier: Programming Language :: Python
Classifier: Framework :: Odoo
Classifier: Framework :: Odoo :: 18.0
Classifier: License :: OSI Approved :: GNU Affero General Public License v3
Classifier: Development Status :: 3 - Alpha
